requirements.txt
setup.cfg
setup.py
docs/astro_data.html
docs/ccsds.html
docs/conversion.html
docs/estimation.html
docs/index.html
docs/propagation.html
docs/utilities.html
docs/version.html
docs/plotting/estimation.html
docs/plotting/index.html
docs/plotting/simulation.html
docs/rpc/conversion_pb2.html
docs/rpc/conversion_pb2_grpc.html
docs/rpc/estimation_pb2.html
docs/rpc/estimation_pb2_grpc.html
docs/rpc/index.html
docs/rpc/messages_pb2.html
docs/rpc/messages_pb2_grpc.html
docs/rpc/propagation_pb2.html
docs/rpc/propagation_pb2_grpc.html
docs/rpc/server.html
docs/rpc/utilities_pb2.html
docs/rpc/utilities_pb2_grpc.html
examples/CAR_MHF.py
examples/CAR_MHF_obs.json
examples/fit_radec.py
examples/interpolate_oem.py
examples/multi_target.py
examples/predict_passes.py
examples/propagate_tle.py
examples/test_conversion.py
examples/test_estimation.py
examples/test_interpolation.py
orbdetpy/__init__.py
orbdetpy/astro_data.py
orbdetpy/ccsds.py
orbdetpy/conversion.py
orbdetpy/estimation.py
orbdetpy/generate_stubs.sh
orbdetpy/propagation.py
orbdetpy/start_server.sh
orbdetpy/utilities.py
orbdetpy/version.py
orbdetpy/orekit-data/SpaceWeather.dat
orbdetpy/orekit-data/fes2004_Cnm-Snm.dat
orbdetpy/orekit-data/tai-utc.dat
orbdetpy/orekit-data/DE-430-ephemerides/lnxp1990.430
orbdetpy/orekit-data/Earth-Orientation-Parameters/IAU-1980/finals.all
orbdetpy/orekit-data/Earth-Orientation-Parameters/IAU-2000/finals2000A.all
orbdetpy/orekit-data/Potential/egm96_to96
orbdetpy/plotting/__init__.py
orbdetpy/plotting/estimation.py
orbdetpy/plotting/simulation.py
orbdetpy/rpc/__init__.py
orbdetpy/rpc/conversion_pb2.py
orbdetpy/rpc/conversion_pb2_grpc.py
orbdetpy/rpc/estimation_pb2.py
orbdetpy/rpc/estimation_pb2_grpc.py
orbdetpy/rpc/messages_pb2.py
orbdetpy/rpc/messages_pb2_grpc.py
orbdetpy/rpc/propagation_pb2.py
orbdetpy/rpc/propagation_pb2_grpc.py
orbdetpy/rpc/server.py
orbdetpy/rpc/utilities_pb2.py
orbdetpy/rpc/utilities_pb2_grpc.py
orbdetpy/target/orbdetpy-server-2.1.0.jar
orbdetpy-2.1.0.dist-info/LICENSE
orbdetpy-2.1.0.dist-info/METADATA
orbdetpy-2.1.0.dist-info/WHEEL
orbdetpy-2.1.0.dist-info/top_level.txt
orbdetpy-2.1.0.dist-info/RECORD
