Metadata-Version: 2.1
Name: orbdetpy
Version: 2.1.0
Summary: Orbit determination routines for Python
Home-page: https://github.com/ut-astria/orbdetpy
Author: Shiva Iyer
Author-email: shiva.iyer@utexas.edu
License: GPLv3+
Project-URL: Documentation, https://ut-astria.github.io/orbdetpy
Project-URL: Source, https://github.com/ut-astria/orbdetpy
Project-URL: Tracker, https://github.com/ut-astria/orbdetpy/issues
Keywords: orbit_determination utilities orbit space celestial_mechanics astrodynamics estimation satellite_tracking pass_prediction
Platform: UNKNOWN
Classifier: Development Status :: 5 - Production/Stable
Classifier: Environment :: Console
Classifier: Intended Audience :: Developers
Classifier: Intended Audience :: Science/Research
Classifier: License :: OSI Approved :: GNU General Public License v3 or later (GPLv3+)
Classifier: Natural Language :: English
Classifier: Operating System :: OS Independent
Classifier: Programming Language :: Python
Classifier: Programming Language :: Python :: 3
Classifier: Programming Language :: Python :: 3.8
Classifier: Programming Language :: Python :: 3.9
Classifier: Programming Language :: Java
Classifier: Topic :: Scientific/Engineering
Classifier: Topic :: Scientific/Engineering :: Astronomy
Classifier: Topic :: Utilities
License-File: LICENSE
Requires-Dist: grpcio (>=1.44.0)
Requires-Dist: grpcio-tools (>=1.44.0)
Requires-Dist: matplotlib (>=3.5.1)
Requires-Dist: numpy (>=1.22.2)
Requires-Dist: protobuf (>=3.19.4)
Requires-Dist: psutil (>=5.9.0)
Requires-Dist: requests (>=2.27.1)
